<?xml version="1.0" encoding="utf-8"?>
<VisualState xmlns:xsi="http://www.w3.org/2001/XMLSchema-instance" xmlns:xsd="http://www.w3.org/2001/XMLSchema" ShowCheckBoxes="false">
  <TopNode>[0-1000]C:\Users\wataru\sendgrid\csharp\v5\sendgrid-csharp\SendGrid\SendGrid.sln</TopNode>
  <SelectedNode>[0-1000]C:\Users\wataru\sendgrid\csharp\v5\sendgrid-csharp\SendGrid\SendGrid.sln</SelectedNode>
  <ExcludeCategories>false</ExcludeCategories>
  <Nodes>
    <Node UniqueName="[0-1000]C:\Users\wataru\sendgrid\csharp\v5\sendgrid-csharp\SendGrid\SendGrid.sln" Expanded="true" />
    <Node UniqueName="[0-1026]C:\Users\wataru\sendgrid\csharp\v5\sendgrid-csharp\SendGrid\Tests\bin\BuildNet45\Tests.dll" Expanded="true" />
    <Node UniqueName="[0-1027]Tests" Expanded="true" />
    <Node UniqueName="[0-1001]Tests.TestSendgrid" Expanded="true" />
    <Node UniqueName="[0-1028]Tests.Transport" Expanded="true" />
    <Node UniqueName="[0-1023]Tests.Transport.TestWebApi" Expanded="true" />
  </Nodes>
</VisualState>